fastapi_typed_client/__init__.py
fastapi_typed_client/__main__.py
fastapi_typed_client/__version__.py
fastapi_typed_client/_core.py
fastapi_typed_client/_generator.py
fastapi_typed_client/_parser.py
fastapi_typed_client/_utils/__init__.py
fastapi_typed_client/_utils/import_.py
fastapi_typed_client/_utils/string.py
fastapi_typed_client/cli.py
fastapi_typed_client/client.py
fastapi_typed_client/py.typed
fastapi_typed_client-0.2.0.dist-info/licenses/LICENSE
fastapi_typed_client-0.2.0.dist-info/WHEEL
fastapi_typed_client-0.2.0.dist-info/entry_points.txt
fastapi_typed_client-0.2.0.dist-info/METADATA
fastapi_typed_client-0.2.0.dist-info/RECORD
