Metadata-Version: 2.4
Name: fastapi-typed-client
Version: 0.2.0
Summary: Generate a fully-typed client for your FastAPI app with the Pydantic models from your code (mostly for testing)
Keywords: fastapi,client,testing,typed,httpx,pydantic,api-client
Author: Lukas Schmelzeisen
Author-email: Lukas Schmelzeisen <me@lschmelzeisen.com>
License-Expression: Apache-2.0
License-File: LICENSE
Classifier: Development Status :: 3 - Alpha
Classifier: Environment :: Web Environment
Classifier: Framework :: AnyIO
Classifier: Framework :: FastAPI
Classifier: Framework :: Pydantic
Classifier: Framework :: Pydantic :: 2
Classifier: Intended Audience :: Developers
Classifier: Intended Audience :: Information Technology
Classifier: Intended Audience :: System Administrators
Classifier: License :: OSI Approved :: Apache Software License
Classifier: Operating System :: OS Independent
Classifier: Programming Language :: Python
Classifier: Programming Language :: Python :: 3
Classifier: Programming Language :: Python :: 3 :: Only
Classifier: Programming Language :: Python :: 3.14
Classifier: Topic :: Internet
Classifier: Topic :: Internet :: WWW/HTTP
Classifier: Topic :: Internet :: WWW/HTTP :: HTTP Servers
Classifier: Topic :: Software Development
Classifier: Topic :: Software Development :: Libraries
Classifier: Topic :: Software Development :: Libraries :: Application Frameworks
Classifier: Topic :: Software Development :: Libraries :: Python Modules
Classifier: Topic :: Software Development :: Testing
Classifier: Topic :: Utilities
Classifier: Typing :: Typed
Requires-Dist: fastapi>=0.128.0
Requires-Dist: httpx>=0.28.1
Requires-Dist: pydantic>=2.12.5
Requires-Dist: rich>=14.2.0
Requires-Dist: typer>=0.21.1
Requires-Python: >=3.14
Project-URL: changelog, https://github.com/lschmelzeisen/fastapi-typed-client/blob/main/CHANGELOG.md
Project-URL: issues, https://github.com/lschmelzeisen/fastapi-typed-client/issues
Project-URL: source, https://github.com/lschmelzeisen/fastapi-typed-client
